AUTHORS
ChangeLog
LICENSE
README.md
TODO.md
requirements.txt
setup.cfg
setup.py
test-requirements.txt
tox.ini
dist/openstack_user_management-0.1.0.dev12.tar.gz
openstack_user_management/__init__.py
openstack_user_management/openstack_user_management.py
openstack_user_management.egg-info/PKG-INFO
openstack_user_management.egg-info/SOURCES.txt
openstack_user_management.egg-info/dependency_links.txt
openstack_user_management.egg-info/entry_points.txt
openstack_user_management.egg-info/not-zip-safe
openstack_user_management.egg-info/pbr.json
openstack_user_management.egg-info/requires.txt
openstack_user_management.egg-info/top_level.txt
openstack_user_management/conf/clouds.yaml
openstack_user_management/connectors/__init__.py
openstack_user_management/connectors/openstack_connector.py
openstack_user_management/tests/__init__.py
openstack_user_management/tests/test_openstack_connector.py
openstack_user_management/utils/__init__.py
openstack_user_management/utils/log.py