Metadata-Version: 1.1
Name: openstack-user-management
Version: 0.1.0.dev4
Summary: OpenStack User Management
Home-page: http://b3lab.org
Author: B3Lab
Author-email: "B3Lab" <info@b3lab.org>
License: Apache-2
Keywords: OpenStack
Platform: Linux
Classifier: Development Status :: 3 - Alpha
Classifier: Environment :: OpenStack
Classifier: Intended Audience :: Information Technology
Classifier: Intended Audience :: System Administrators
Classifier: License :: Freeware
Classifier: Operating System :: POSIX :: Linux
Classifier: Programming Language :: Python
Classifier: Programming Language :: Python :: 2
Classifier: Programming Language :: Python :: 2.7
Classifier: Development Status :: 1 - Planning
Classifier: Development Status :: 2 - Pre-Alpha
Classifier: Development Status :: 3 - Alpha
Classifier: Development Status :: 4 - Beta
Classifier: Development Status :: 5 - Production/Stable
Classifier: Development Status :: 6 - Mature
Classifier: Development Status :: 7 - Inactive
Provides: TBF
Obsoletes: TBF
